lib3to6/__init__.py
lib3to6/__main__.py
lib3to6/checker_base.py
lib3to6/checkers.py
lib3to6/checkers_backports.py
lib3to6/common.py
lib3to6/fixer_base.py
lib3to6/fixers.py
lib3to6/fixers_builtin_rename.py
lib3to6/fixers_fstring.py
lib3to6/fixers_future.py
lib3to6/fixers_import_fallback.py
lib3to6/fixers_namedexpr.py
lib3to6/fixers_unpacking_generalization.py
lib3to6/packaging.py
lib3to6/transpile.py
lib3to6/utils.py
lib3to6-202107.1047.dist-info/LICENSE
lib3to6-202107.1047.dist-info/METADATA
lib3to6-202107.1047.dist-info/WHEEL
lib3to6-202107.1047.dist-info/entry_points.txt
lib3to6-202107.1047.dist-info/top_level.txt
lib3to6-202107.1047.dist-info/zip-safe
lib3to6-202107.1047.dist-info/RECORD
