Metadata-Version: 2.1
Name: lib3to6
Version: 202107.1047
Summary: Compile Python 3.6+ code to Python 2.7+
Home-page: https://github.com/mbarkhau/lib3to6
Author: Manuel Barkhau
Author-email: mbarkhau@gmail.com
License: MIT
Keywords: six lib2to3 astor ast
Platform: UNKNOWN
Classifier: Development Status :: 4 - Beta
Classifier: Environment :: Console
Classifier: Environment :: Other Environment
Classifier: Intended Audience :: Developers
Classifier: License :: OSI Approved :: MIT License
Classifier: Operating System :: Unix
Classifier: Operating System :: POSIX
Classifier: Operating System :: Microsoft :: Windows
Classifier: Operating System :: MacOS :: MacOS X
Classifier: Programming Language :: Python
Classifier: Programming Language :: Python :: 3.6
Classifier: Programming Language :: Python :: 3.7
Classifier: Programming Language :: Python :: 3.8
Classifier: Programming Language :: Python :: 3.9
Classifier: Programming Language :: Python :: Implementation :: CPython
Classifier: Topic :: Software Development :: Libraries
Classifier: Topic :: Software Development :: Libraries :: Python Modules
Requires-Python: >=3.6
License-File: LICENSE
Requires-Dist: pathlib2
Requires-Dist: astor
Requires-Dist: wheel
Requires-Dist: typing ; python_version < "3.5"
Requires-Dist: click (<8.0) ; python_version < "3.6"
Requires-Dist: click ; python_version >= "3.6"
